change_base/__init__.py
change_base/change_base.py
change_base-0.0.1.dist-info/LICENSE.txt
change_base-0.0.1.dist-info/METADATA
change_base-0.0.1.dist-info/WHEEL
change_base-0.0.1.dist-info/top_level.txt
change_base-0.0.1.dist-info/RECORD
