Metadata-Version: 2.1
Name: change-base
Version: 0.0.1
Summary: Allows the conversion of a value with any base to the corresponding value in any other base-system
Home-page: https://github.com/
Author: Tabish Mir
Author-email: taabishm2@gmail.com
License: UNKNOWN
Platform: UNKNOWN
Classifier: Programming Language :: Python :: 3
Classifier: License :: OSI Approved :: MIT License
Classifier: Operating System :: OS Independent
